{
  "hash": "3b05b109",
  "configHash": "fb7c4892",
  "lockfileHash": "9a4da37a",
  "browserHash": "a83ac470",
  "optimized": {
    "react/jsx-dev-runtime": {
      "src": "../../node_modules/react/jsx-dev-runtime.js",
      "file": "react_jsx-dev-runtime.js",
      "fileHash": "43beb042",
      "needsInterop": true
    },
    "react": {
      "src": "../../node_modules/react/index.js",
      "file": "react.js",
      "fileHash": "79b11414",
      "needsInterop": true
    },
    "react-dom/client": {
      "src": "../../node_modules/react-dom/client.js",
      "file": "react-dom_client.js",
      "fileHash": "000888b9",
      "needsInterop": true
    }
  },
  "chunks": {
    "chunk-O5RE5CKT": {
      "file": "chunk-O5RE5CKT.js"
    }
  }
}